{
  "movies": [
    {
      "id": "qrtpKnAzVPY",
      "name": "Köstebekgiller 2: Gölgenin Tılsımı | Türk Filmi Full İzle (HD)",
      "thumb": "https://i.ytimg.com/vi/qrtpKnAzVPY/hqdefault.jpg",
      "dur": "1:22:47"
    },
    {
      "id": "3Mku1XRt_X0",
      "name": "Köstebekgiller Perili Orman | Türk Filmi Full İzle (HD)",
      "thumb": "https://i.ytimg.com/vi/3Mku1XRt_X0/hqdefault.jpg",
      "dur": "1:22:51"
    },
    {
      "id": "wW4GEY1GULc",
      "name": "Yürek Yarası | Kadir İnanır Türk Filmi Full İzle (Restorasyonlu)",
      "thumb": "https://i.ytimg.com/vi/wW4GEY1GULc/hqdefault.jpg",
      "dur": "1:23:31"
    },
    {
      "id": "oTDfYKnao9w",
      "name": "Biz Bir Aileyiz | Cüneyt Arkın, Serpil Çakmaklı Eski Türk Filmi Full İzle",
      "thumb": "https://i.ytimg.com/vi/oTDfYKnao9w/hqdefault.jpg",
      "dur": "1:16:58"
    },
    {
      "id": "u2k_4u84I60",
      "name": "Tanrı Misafiri | Ömer Dönmez, Hülya Koçyiğit Eski Türk Filmi Full İzle",
      "thumb": "https://i.ytimg.com/vi/u2k_4u84I60/hqdefault.jpg",
      "dur": "1:17:17"
    },
    {
      "id": "u2k_4u84I60",
      "name": "Tanrı Misafiri | Ömer Dönmez, Hülya Koçyiğit Eski Türk Filmi Full İzle",
      "thumb": "https://i.ytimg.com/vi/u2k_4u84I60/hqdefault.jpg",
      "dur": "1:17:17"
    },
    {
      "id": "bdqcN05uH34",
      "name": "Bak Yeşil Yeşil | Ahmet Özhan Eski Türk Filmi Full İzle",
      "thumb": "https://i.ytimg.com/vi/bdqcN05uH34/hqdefault.jpg",
      "dur": "45:09"
    },
    {
      "id": "I6sYlKnIKmY",
      "name": "Çılgın Kamp | Türk Komedi Filmi Full İzle",
      "thumb": "https://i.ytimg.com/vi/I6sYlKnIKmY/hqdefault.jpg",
      "dur": "1:08:52"
    },
    {
      "id": "r5_kxiuOYQ4",
      "name": "Bir Damla Aşk | Türk Komedi Filmi Full İzle",
      "thumb": "https://i.ytimg.com/vi/r5_kxiuOYQ4/hqdefault.jpg",
      "dur": "1:38:07"
    },
    {
      "id": "F5i4voPHNcY",
      "name": "Vay Başıma Gelenler 2 Buçuk | Türk Komedi Filmi Full İzle",
      "thumb": "https://i.ytimg.com/vi/F5i4voPHNcY/hqdefault.jpg",
      "dur": "1:38:59"
    },
    {
      "id": "i1hpjAsfV64",
      "name": "Boş Çerçeve | Hülya Koçyiğit Kartal Tibet | Full Film İzle",
      "thumb": "https://i.ytimg.com/vi/i1hpjAsfV64/hqdefault.jpg",
      "dur": "1:22:07"
    },
    {
      "id": "L1SpGjL4o0E",
      "name": "Bülbül Yuvası | Türkan Şoray | Full Film İzle",
      "thumb": "https://i.ytimg.com/vi/L1SpGjL4o0E/hqdefault.jpg",
      "dur": "1:26:17"
    },
    {
      "id": "PEh9rQ-B-xk",
      "name": "Kızım Ayşe | Yıldız Kenter Necla Nazır Restorasyonlu Türk Filmi | Full HD Film İzle",
      "thumb": "https://i.ytimg.com/vi/PEh9rQ-B-xk/hqdefault.jpg",
      "dur": "1:31:35"
    },
    {
      "id": "Q4amEPexIZY",
      "name": "Yetimler Okusun | Fikret Hakan Eski Türk Filmi | Full Film İzle",
      "thumb": "https://i.ytimg.com/vi/Q4amEPexIZY/hqdefault.jpg",
      "dur": "1:17:19"
    },
    {
      "id": "LVV5t-F6V6Y",
      "name": "Gelin Çiçeği | Türkan Şoray Kartal Tibet Eski Türk Filmi | Full Film İzle",
      "thumb": "https://i.ytimg.com/vi/LVV5t-F6V6Y/hqdefault.jpg",
      "dur": "1:28:28"
    },
    {
      "id": "7cNb5DNwSgM",
      "name": "Küçük Hanımın Şoförü | Ayhan Işık Belgin Doruk Eski Türk Filmi | Full Film İzle",
      "thumb": "https://i.ytimg.com/vi/7cNb5DNwSgM/hqdefault.jpg",
      "dur": "1:32:13"
    },
    {
      "id": "ViyqrKBOpQU",
      "name": "Tek Başına | Cüneyt Arkın Filmi | Full Film İzle",
      "thumb": "https://i.ytimg.com/vi/ViyqrKBOpQU/hqdefault.jpg",
      "dur": "1:14:13"
    },
    {
      "id": "sHmx1f9jGFE",
      "name": "Sen Bir Meleksin | Hülya Koçyiğit Eski Türk Filmi Tek Parça",
      "thumb": "https://i.ytimg.com/vi/sHmx1f9jGFE/hqdefault.jpg",
      "dur": "1:28:42"
    },
    {
      "id": "kj4-yTaHC5I",
      "name": "HÜDAVERDİ PIRTIK 🤣 KOMEDİ FİLMİ",
      "thumb": "https://i.ytimg.com/vi/kj4-yTaHC5I/hqdefault.jpg",
      "dur": "1:17:01"
    },
    {
      "id": "CedlJjDRJfA",
      "name": "Perili Orman 👼 Yerli Film",
      "thumb": "https://i.ytimg.com/vi/CedlJjDRJfA/hqdefault.jpg",
      "dur": "1:22:52"
    },
    {
      "id": "nz5_bcxpbMU",
      "name": "Sorma Neden 💯😂 TÜRK KOMEDİ FİLMİ",
      "thumb": "https://i.ytimg.com/vi/nz5_bcxpbMU/hqdefault.jpg",
      "dur": "1:16:08"
    },
    {
      "id": "FeeqRGiGB6g",
      "name": "Delisin Delisin 🤪🤪 TÜRK KOMEDİ FİLMİ",
      "thumb": "https://i.ytimg.com/vi/FeeqRGiGB6g/hqdefault.jpg",
      "dur": "1:11:29"
    },
    {
      "id": "v9QNVa6I4mM",
      "name": "Kızım ve Ben 🚨 Aksiyon Filmi",
      "thumb": "https://i.ytimg.com/vi/v9QNVa6I4mM/hqdefault.jpg",
      "dur": "1:47:16"
    },
    {
      "id": "fSJrGbn_b1E",
      "name": "Baş Belası | Selen Seyven Çetin Altay | Türk Komedi Filmi | Full Film İzle",
      "thumb": "https://i.ytimg.com/vi/fSJrGbn_b1E/hqdefault.jpg",
      "dur": "1:15:27"
    },
    {
      "id": "8nj_CK_pSNo",
      "name": "Tutmayın Beni | Yerli Komedi Filmi | Full Film İzle",
      "thumb": "https://i.ytimg.com/vi/8nj_CK_pSNo/hqdefault.jpg",
      "dur": "1:46:50"
    },
    {
      "id": "rmaINfGNdGk",
      "name": "İkizler Firarda | Yerli Aile Filmi | Full Film İzle",
      "thumb": "https://i.ytimg.com/vi/rmaINfGNdGk/hqdefault.jpg",
      "dur": "1:34:17"
    },
    {
      "id": "uxrQ4FtKabU",
      "name": "Kendime İyi Bak | Türk Aile Filmi Romantik Komedi Full Film İzle",
      "thumb": "https://i.ytimg.com/vi/uxrQ4FtKabU/hqdefault.jpg",
      "dur": "1:19:50"
    },
    {
      "id": "3VxpSM88xIg",
      "name": "Sarıkamış Çocukları Türk Dram Filmi | Full Film İzle",
      "thumb": "https://i.ytimg.com/vi/3VxpSM88xIg/hqdefault.jpg",
      "dur": "1:28:19"
    },
    {
      "id": "tg2O6j8Vam4",
      "name": "Süper İncir | Yerli Aile Filmi | Full Film İzle",
      "thumb": "https://i.ytimg.com/vi/tg2O6j8Vam4/hqdefault.jpg",
      "dur": "1:30:10"
    },
    {
      "id": "vYj-76esTK8",
      "name": "120 | Özge Özberk Burak Sergen Yerli Dram Filmi",
      "thumb": "https://i.ytimg.com/vi/vYj-76esTK8/hqdefault.jpg",
      "dur": "1:44:18"
    },
    {
      "id": "9V5q-6IFfDU",
      "name": "Aşkopat | Doğuş Yerli Romantik Komedi Filmi | Full Film İzle",
      "thumb": "https://i.ytimg.com/vi/9V5q-6IFfDU/hqdefault.jpg",
      "dur": "1:30:56"
    },
    {
      "id": "k_3zH_Q3u0c",
      "name": "Geniş Aile: Yapıştır! | Ufuk Özkan Fırat Tanış | Yerli Aile Filmi | Full Film İzle",
      "thumb": "https://i.ytimg.com/vi/k_3zH_Q3u0c/hqdefault.jpg",
      "dur": "1:32:35"
    },
    {
      "id": "9uSkwsKTYG4",
      "name": "Bana Git De | Tayanç Ayaydın Atiye | Türk Dram Filmi | Full Film İzle",
      "thumb": "https://i.ytimg.com/vi/9uSkwsKTYG4/hqdefault.jpg",
      "dur": "1:37:36"
    },
    {
      "id": "ZhP4S2LMOrw",
      "name": "Geniş Aile 2: Her Türlü | Ufuk Özkan Fırat Tanış | Yerli Aile Filmi | Full Film İzle",
      "thumb": "https://i.ytimg.com/vi/ZhP4S2LMOrw/hqdefault.jpg",
      "dur": "1:30:16"
    },
    {
      "id": "wem_5AFiN9o",
      "name": "Memleket Meselesi | Yerli Aile Filmi",
      "thumb": "https://i.ytimg.com/vi/wem_5AFiN9o/hqdefault.jpg",
      "dur": "1:38:07"
    },
    {
      "id": "BDs7gj4kzyI",
      "name": "Afacanlar Sınıfı 2008 | Cüneyt Arkın Hande Kazanova Yerli Aile Filmi | Full Film İzle",
      "thumb": "https://i.ytimg.com/vi/BDs7gj4kzyI/hqdefault.jpg",
      "dur": "1:36:17"
    },
    {
      "id": "sFlCfjR2Llc",
      "name": "Pamuk Prenses ve Yedi Cüceler | Eski Türk Aile Filmi | Full İzle",
      "thumb": "https://i.ytimg.com/vi/sFlCfjR2Llc/hqdefault.jpg",
      "dur": "1:29:06"
    },
    {
      "id": "q2gb-L5I99M",
      "name": "Afacan Ateş Parçası | Türk Aile Filmi | Full Film İzle",
      "thumb": "https://i.ytimg.com/vi/q2gb-L5I99M/hqdefault.jpg",
      "dur": "1:18:25"
    },
    {
      "id": "oIv0fcuwhaU",
      "name": "Çalgı Çengi | Ahmet Kural, Murat Cemcir Türk Komedi Filmi",
      "thumb": "https://i.ytimg.com/vi/oIv0fcuwhaU/hqdefault.jpg",
      "dur": "1:21:19"
    },
    {
      "id": "Da-23bxfevM",
      "name": "Bir Damla Aşk | Türk Komedi Filmi Full İzle",
      "thumb": "https://i.ytimg.com/vi/Da-23bxfevM/hqdefault.jpg",
      "dur": "1:38:42"
    },
    {
      "id": "oPIQ3oF45yY",
      "name": "Mumya Firarda | Tek Parça",
      "thumb": "https://i.ytimg.com/vi/oPIQ3oF45yY/hqdefault.jpg",
      "dur": "1:43:08"
    },
    {
      "id": "ABltZDlzJDg",
      "name": "Hakanlar Çarpışıyor | Cüneyt Arkın Türk Aksiyon Filmi | Full Film İzle",
      "thumb": "https://i.ytimg.com/vi/ABltZDlzJDg/hqdefault.jpg",
      "dur": "1:12:20"
    },
    {
      "id": "PgXDCtNFOa4",
      "name": "Dağların Kartalı | Ayhan Işık Kadir İnanır Türk Aksiyon Filmi | Full İzle",
      "thumb": "https://i.ytimg.com/vi/PgXDCtNFOa4/hqdefault.jpg",
      "dur": "58:21"
    },
    {
      "id": "1wlyowORRwU",
      "name": "Kanun Gücü | Cüneyt Arkın Türk Aksiyon Filmi (Restorasyonlu)",
      "thumb": "https://i.ytimg.com/vi/1wlyowORRwU/hqdefault.jpg",
      "dur": "1:17:21"
    },
    {
      "id": "Y3BYiA_qGlQ",
      "name": "Babaların Babası | Cüneyt Arkın Aksiyon Filmi Full İzle",
      "thumb": "https://i.ytimg.com/vi/Y3BYiA_qGlQ/hqdefault.jpg",
      "dur": "1:22:48"
    },
    {
      "id": "cepubL1A3mQ",
      "name": "Ana Ocağı | Fatma Girik Kadir İnanır Türk Aksiyon Filmi (Restorasyonlu)",
      "thumb": "https://i.ytimg.com/vi/cepubL1A3mQ/hqdefault.jpg",
      "dur": "1:24:16"
    },
    {
      "id": "yeGaxq0R5U4",
      "name": "İnsan Avcısı | Cüneyt Arkın Aksiyon Filmi Full İzle (Restorasyonlu)",
      "thumb": "https://i.ytimg.com/vi/yeGaxq0R5U4/hqdefault.jpg",
      "dur": "1:26:42"
    },
    {
      "id": "Zmu79nDuY1Q",
      "name": "Toprak Ana | Fatma Girik Eski Türk Aksiyon Filmi",
      "thumb": "https://i.ytimg.com/vi/Zmu79nDuY1Q/hqdefault.jpg",
      "dur": "1:37:01"
    },
    {
      "id": "12wAh9LcR8s",
      "name": "Kılıç Aslan | Full Film Tek Parça İzle",
      "thumb": "https://i.ytimg.com/vi/12wAh9LcR8s/hqdefault.jpg",
      "dur": "1:21:36"
    },
    {
      "id": "TOujPqbzyck",
      "name": "Kaos : Örümcek Ağı | Full Film Tek Parça İzle",
      "thumb": "https://i.ytimg.com/vi/TOujPqbzyck/hqdefault.jpg",
      "dur": "1:34:23"
    },
    {
      "id": "G9cxvS9wH04",
      "name": "Gecelerin Hakimi | Full Film Tek Parça İzle",
      "thumb": "https://i.ytimg.com/vi/G9cxvS9wH04/hqdefault.jpg",
      "dur": "54:52"
    },
    {
      "id": "ymWZbr9qdeY",
      "name": "Korkusuz Cengaver | Full Film Tek Parça İzle",
      "thumb": "https://i.ytimg.com/vi/ymWZbr9qdeY/hqdefault.jpg",
      "dur": "1:23:30"
    },
    {
      "id": "Dbl1oMwmSm0",
      "name": "Çöl Kartalı | Full Film Tek Parça İzle",
      "thumb": "https://i.ytimg.com/vi/Dbl1oMwmSm0/hqdefault.jpg",
      "dur": "1:24:12"
    },
    {
      "id": "oFlw6ElOxtQ",
      "name": "Battal Gazi'nin Oğlu | Full Film Tek Parça İzle",
      "thumb": "https://i.ytimg.com/vi/oFlw6ElOxtQ/hqdefault.jpg",
      "dur": "1:12:14"
    },
    {
      "id": "ztoFW0ob3w8",
      "name": "Cengiz Han'ın Fedaisi | Full Film Tek Parça İzle",
      "thumb": "https://i.ytimg.com/vi/ztoFW0ob3w8/hqdefault.jpg",
      "dur": "1:11:23"
    },
    {
      "id": "SekQs752tfA",
      "name": "Battal Gazi Destanı | Full Film Tek Parça İzle",
      "thumb": "https://i.ytimg.com/vi/SekQs752tfA/hqdefault.jpg",
      "dur": "1:17:54"
    },
    {
      "id": "07sy0hX_dU4",
      "name": "Kabadayı | Full Film Tek Parça İzle",
      "thumb": "https://i.ytimg.com/vi/07sy0hX_dU4/hqdefault.jpg",
      "dur": "2:17:30"
    },
    {
      "id": "zDB6e3jz50w",
      "name": "Karınca Kapanı | Full Film Tek Parça İzle",
      "thumb": "https://i.ytimg.com/vi/zDB6e3jz50w/hqdefault.jpg",
      "dur": "1:27:17"
    },
    {
      "id": "kv3cxUOJVfU",
      "name": "Kanunsuzlar | Full Film Tek Parça İzle",
      "thumb": "https://i.ytimg.com/vi/kv3cxUOJVfU/hqdefault.jpg",
      "dur": "1:17:21"
    },
    {
      "id": "ieiQggJhStI",
      "name": "Behzat Ç. - Ankara Yanıyor | Full Film Tek Parça İzle",
      "thumb": "https://i.ytimg.com/vi/ieiQggJhStI/hqdefault.jpg",
      "dur": "1:32:57"
    },
    {
      "id": "Xa1odMo9pLg",
      "name": "Behzat Ç. Ankara Yanıyor | Türk Filmi Tek Parça (HD)",
      "thumb": "https://i.ytimg.com/vi/Xa1odMo9pLg/hqdefault.jpg",
      "dur": "1:34:39"
    },
    {
      "id": "KymIj6z_pE0",
      "name": "Kanunsuzlar | Türk Filmi Tek Parça (HD)",
      "thumb": "https://i.ytimg.com/vi/KymIj6z_pE0/hqdefault.jpg",
      "dur": "1:18:34"
    },
    {
      "id": "Z_Du916CktU",
      "name": "Battal Gazi'nin Oğlu (Restorasyonlu) | Cüneyt Arkın Filmi | Full Film İzle",
      "thumb": "https://i.ytimg.com/vi/Z_Du916CktU/hqdefault.jpg",
      "dur": "1:09:57"
    },
    {
      "id": "bT3tI9eOGAk",
      "name": "Kartal Bey | Cüneyt Arkın Eski Türk Filmi Tek Parça",
      "thumb": "https://i.ytimg.com/vi/bT3tI9eOGAk/hqdefault.jpg",
      "dur": "1:08:47"
    },
    {
      "id": "5_gvSqxTO0U",
      "name": "Sert Adam | Cüneyt Arkın Eski Türk Filmi Full İzle",
      "thumb": "https://i.ytimg.com/vi/5_gvSqxTO0U/hqdefault.jpg",
      "dur": "1:13:46"
    },
    {
      "id": "8fy52sGg-ng",
      "name": "Behzat Ç. Ankara Yanıyor 🚨 Aksiyon Filmi",
      "thumb": "https://i.ytimg.com/vi/8fy52sGg-ng/hqdefault.jpg",
      "dur": "1:32:46"
    },
    {
      "id": "Yzc1bV1mpi4",
      "name": "Cinayetin Sırrı ⚡ Nuri Alço",
      "thumb": "https://i.ytimg.com/vi/Yzc1bV1mpi4/hqdefault.jpg",
      "dur": "1:23:05"
    },
    {
      "id": "95Q3Fq2Teig",
      "name": "Kabadayı | Şener Şen Kenan İmirzalıoğlu Türk Dram Filmi | Full İzle",
      "thumb": "https://i.ytimg.com/vi/95Q3Fq2Teig/hqdefault.jpg",
      "dur": "2:16:55"
    },
    {
      "id": "m3Dm7hLQNZI",
      "name": "Yarınsız Adam | Cüneyt Arkın Eski Türk Filmi Full izle",
      "thumb": "https://i.ytimg.com/vi/m3Dm7hLQNZI/hqdefault.jpg",
      "dur": "1:08:51"
    },
    {
      "id": "4kBe2xNxX-Q",
      "name": "Sihirli Lamba 🪔 Fantastik Film",
      "thumb": "https://i.ytimg.com/vi/4kBe2xNxX-Q/hqdefault.jpg",
      "dur": "1:14:20"
    },
    {
      "id": "UlBAzdLyTco",
      "name": "Üç Dev Adam | Eski Türk Filmi Tek Parça",
      "thumb": "https://i.ytimg.com/vi/UlBAzdLyTco/hqdefault.jpg",
      "dur": "1:09:52"
    },
    {
      "id": "h0FrNkNQweM",
      "name": "Kara Şimşek | Sümer Tilmaç Türk Filmi Tek Parça",
      "thumb": "https://i.ytimg.com/vi/h0FrNkNQweM/hqdefault.jpg",
      "dur": "1:07:39"
    },
    {
      "id": "mkU2qlu4Zgc",
      "name": "Parola Kartal 🦅 Karaca Kaan",
      "thumb": "https://i.ytimg.com/vi/mkU2qlu4Zgc/hqdefault.jpg",
      "dur": "59:59"
    },
    {
      "id": "PH1Jc3A_VMk",
      "name": "Asi Kabadayı | Filiz Taçbaş Türk Filmi Tek Parça",
      "thumb": "https://i.ytimg.com/vi/PH1Jc3A_VMk/hqdefault.jpg",
      "dur": "1:16:00"
    },
    {
      "id": "EAClNGY_e00",
      "name": "Erkekçe | Cüneyt Arkın Türk Filmi Tek Parça",
      "thumb": "https://i.ytimg.com/vi/EAClNGY_e00/hqdefault.jpg",
      "dur": "1:16:19"
    },
    {
      "id": "O8b5O9t_lFs",
      "name": "AKREP YUVASI 🦂 BANU ALKAN CÜNEYT ARKIN AKSİYON FİLMİ 🔥",
      "thumb": "https://i.ytimg.com/vi/O8b5O9t_lFs/hqdefault.jpg",
      "dur": "1:26:49"
    },
    {
      "id": "5fzOUaBeJmQ",
      "name": "Parola Kartal | Aysun Güven Eski Türk Filmi Tek Parça",
      "thumb": "https://i.ytimg.com/vi/5fzOUaBeJmQ/hqdefault.jpg",
      "dur": "59:41"
    },
    {
      "id": "wJjZbG4_aTA",
      "name": "Sonsuz Sokaklar 💣 Kazım Kartal",
      "thumb": "https://i.ytimg.com/vi/wJjZbG4_aTA/hqdefault.jpg",
      "dur": "50:39"
    },
    {
      "id": "ZtYrRFOZnYM",
      "name": "Aç Kartallar 🥋 Yerli Dövüş Filmi",
      "thumb": "https://i.ytimg.com/vi/ZtYrRFOZnYM/hqdefault.jpg",
      "dur": "1:17:47"
    },
    {
      "id": "V2rXcMl5P_c",
      "name": "40 (KIRK) 🚬 ALİ ATAY FİLMİ",
      "thumb": "https://i.ytimg.com/vi/V2rXcMl5P_c/hqdefault.jpg",
      "dur": "1:17:53"
    },
    {
      "id": "ja23xlG7qMk",
      "name": "Süpermen Dönüyor | Yerli Aksiyon Filmi",
      "thumb": "https://i.ytimg.com/vi/ja23xlG7qMk/hqdefault.jpg",
      "dur": "1:05:35"
    },
    {
      "id": "uuDIT5b0-s8",
      "name": "Kahramanlar Bayrak | Fikret Hakan Eski Türk Filmi",
      "thumb": "https://i.ytimg.com/vi/uuDIT5b0-s8/hqdefault.jpg",
      "dur": "1:15:03"
    },
    {
      "id": "Ox4Xpnbzeuc",
      "name": "Üç Süpermen Olimpiyatlarda | Yerli Aksiyon Filmi",
      "thumb": "https://i.ytimg.com/vi/Ox4Xpnbzeuc/hqdefault.jpg",
      "dur": "59:42"
    },
    {
      "id": "vEqQIpYe9a0",
      "name": "Hırsız Milyoner | Elif Pektaş Eski Türk Filmi Full İzle",
      "thumb": "https://i.ytimg.com/vi/vEqQIpYe9a0/hqdefault.jpg",
      "dur": "1:00:40"
    },
    {
      "id": "4AhYyVuGQgU",
      "name": "Kaos: Örümcek Ağı | Yerli Aksiyon Filmi | Full Film İzle",
      "thumb": "https://i.ytimg.com/vi/4AhYyVuGQgU/hqdefault.jpg",
      "dur": "1:29:43"
    },
    {
      "id": "f-PoVNY7n4I",
      "name": "Miras | Yerli Aksiyon Filmi",
      "thumb": "https://i.ytimg.com/vi/f-PoVNY7n4I/hqdefault.jpg",
      "dur": "1:27:17"
    }
  ]
}